Metadata-Version: 2.1
Name: pyalpm
Version: 0.10.6
Summary: libalpm bindings for Python 3
Home-page: https://gitlab.archlinux.org/archlinux/pyalpm
Author: Rémy Oudompheng
Author-email: remy@archlinux.org
License: GPLv3+
Keywords: archlinux,pacman
Platform: UNKNOWN
Classifier: Development Status :: 6 - Mature
Classifier: License :: OSI Approved :: GNU General Public License v3 or later (GPLv3+)
Classifier: Programming Language :: C
Classifier: Programming Language :: Python :: 3 :: Only
Classifier: Topic :: System :: Archiving :: Packaging
Classifier: Topic :: System :: Software Distribution
Classifier: Topic :: System :: Systems Administration
License-File: LICENSE
License-File: AUTHORS
